aigohotel_mcp/__init__.py
aigohotel_mcp/server.py
aigohotel_mcp-0.1.0.dist-info/METADATA
aigohotel_mcp-0.1.0.dist-info/WHEEL
aigohotel_mcp-0.1.0.dist-info/entry_points.txt
aigohotel_mcp-0.1.0.dist-info/licenses/LICENSE
aigohotel_mcp-0.1.0.dist-info/RECORD
