Metadata-Version: 2.4
Name: aigohotel-mcp
Version: 0.1.0
Summary: MCP server for global hotel search powered by AIGOHOTEL API
Project-URL: Homepage, https://github.com/longcreat/aigohotel-mcp
Project-URL: Documentation, https://github.com/longcreat/aigohotel-mcp#readme
Project-URL: Repository, https://github.com/longcreat/aigohotel-mcp
Project-URL: Issues, https://github.com/longcreat/aigohotel-mcp/issues
Project-URL: API Key Application, https://mcp.agentichotel.cn/apply
Author-email: zlon <dreamtzlong@gmail.com>
License: MIT
License-File: LICENSE
Keywords: aigohotel,fastmcp,hotel,mcp,model-context-protocol,search
Classifier: Development Status :: 4 - Beta
Classifier: Intended Audience :: Developers
Classifier: License :: OSI Approved :: MIT License
Classifier: Programming Language :: Python :: 3
Classifier: Programming Language :: Python :: 3.12
Classifier: Programming Language :: Python :: 3.13
Classifier: Topic :: Internet :: WWW/HTTP
Classifier: Topic :: Software Development :: Libraries :: Python Modules
Requires-Python: >=3.12
Requires-Dist: fastmcp>=2.7.0
Requires-Dist: httpx>=0.27.0
